{
  "project_info": {
    "project_number": "238896112560",
    "project_id": "adfaber-1246b",
    "storage_bucket": "adfaber-1246b.appspot.com"
  },
  "client": [
    {
      "client_info": {
        "mobilesdk_app_id": "1:238896112560:android:9884263feff09e4880ac75",
        "android_client_info": {
          "package_name": "com.example.lectia2"
        }
      },
      "oauth_client": [
        {
          "client_id": "238896112560-j2ntoa6nogsiqlhbem0v9tfe2acvhev1.apps.googleusercontent.com",
          "client_type": 3
        }
      ],
      "api_key": [
        {
          "current_key": "AIzaSyAN-xia0aKJPUjho4wsJlvlO41sIKt_ga4"
        }
      ],
      "services": {
        "appinvite_service": {
          "other_platform_oauth_client": [
            {
              "client_id": "238896112560-j2ntoa6nogsiqlhbem0v9tfe2acvhev1.apps.googleusercontent.com",
              "client_type": 3
            }
          ]
        }
      }
    }
  ],
  "configuration_version": "1"
}